setup.py
ItChatSh.egg-info/PKG-INFO
ItChatSh.egg-info/SOURCES.txt
ItChatSh.egg-info/dependency_links.txt
ItChatSh.egg-info/requires.txt
ItChatSh.egg-info/top_level.txt
itchatsh/__init__.py