Metadata-Version: 1.0
Name: ItChatSh
Version: 1.0.6
Summary: Shell on WeChat based on ItChat
Home-page: https://github.com/lizeyan/itchatsh
Author: LI ZEYAN
Author-email: zy-li14@hotmail.com
License: MIT
Platform: UNKNOWN
